dcs_api_client/__init__.py
dcs_api_client/api_client.py
dcs_api_client/configuration.py
dcs_api_client/rest.py
dcs_api_client/api/__init__.py
dcs_api_client/api/activitypub_api.py
dcs_api_client/api/admin_api.py
dcs_api_client/api/catalog_api.py
dcs_api_client/api/issue_api.py
dcs_api_client/api/miscellaneous_api.py
dcs_api_client/api/notification_api.py
dcs_api_client/api/organization_api.py
dcs_api_client/api/package_api.py
dcs_api_client/api/repository_api.py
dcs_api_client/api/settings_api.py
dcs_api_client/api/user_api.py
dcs_api_client/models/__init__.py
dcs_api_client/models/access_token.py
dcs_api_client/models/activity.py
dcs_api_client/models/activity_pub.py
dcs_api_client/models/add_collaborator_option.py
dcs_api_client/models/add_time_option.py
dcs_api_client/models/annotated_tag.py
dcs_api_client/models/annotated_tag_object.py
dcs_api_client/models/api_error.py
dcs_api_client/models/attachment.py
dcs_api_client/models/branch.py
dcs_api_client/models/branch_protection.py
dcs_api_client/models/catalog_entry.py
dcs_api_client/models/catalog_search_results.py
dcs_api_client/models/catalog_stage.py
dcs_api_client/models/catalog_stages.py
dcs_api_client/models/change_file_operation.py
dcs_api_client/models/change_files_options.py
dcs_api_client/models/changed_file.py
dcs_api_client/models/combined_status.py
dcs_api_client/models/comment.py
dcs_api_client/models/commit.py
dcs_api_client/models/commit_affected_files.py
dcs_api_client/models/commit_date_options.py
dcs_api_client/models/commit_meta.py
dcs_api_client/models/commit_stats.py
dcs_api_client/models/commit_status.py
dcs_api_client/models/commit_status_state.py
dcs_api_client/models/commit_user.py
dcs_api_client/models/contents_response.py
dcs_api_client/models/create_access_token_option.py
dcs_api_client/models/create_branch_protection_option.py
dcs_api_client/models/create_branch_repo_option.py
dcs_api_client/models/create_email_option.py
dcs_api_client/models/create_file_options.py
dcs_api_client-1.20.3.dist-info/METADATA
dcs_api_client-1.20.3.dist-info/WHEEL
dcs_api_client-1.20.3.dist-info/top_level.txt
dcs_api_client-1.20.3.dist-info/RECORD
