Metadata-Version: 2.1
Name: dcs-api-client
Version: 1.20.3
Summary: DCS (Gitea) API.
Home-page: https://github.com/unfoldingWord/python-dcs-api-client
Author-email: 
Keywords: Swagger,DCS (Gitea) API.
Requires-Dist: certifi >=2017.4.17
Requires-Dist: python-dateutil >=2.1
Requires-Dist: six >=1.10
Requires-Dist: urllib3 >=1.23
